example_package/__init__.py
hello_leesung02/__init__.py
hello_leesung02/who.py
hello_LEESUNG02-0.2.1.dist-info/METADATA
hello_LEESUNG02-0.2.1.dist-info/WHEEL
hello_LEESUNG02-0.2.1.dist-info/top_level.txt
hello_LEESUNG02-0.2.1.dist-info/RECORD
