Metadata-Version: 2.1
Name: hello_LEESUNG02
Version: 0.2.1
Summary: TRUE
Author-email: LEESUNG02 <leesung02@naver.com>
License: MIT
Requires-Python: >=3.8
